Workbook

Sheet Welcome
B2: HELIX MEDTECH — STRATEGY SIMULATION
B3: Medical devices (the core to exploit) + a digital-health SaaS platform (the growth engine) — three rounds.
B5: The brief
B6: You are the executive team of Helix MedTech. Your mature medical-devices business throws off cash but is under attack from AI diagnostics and connected-device entrants. Your digital-health SaaS platform is small but growing fast and is what investors reward. Across three rounds you make seven strategic decisions each round. The model converts them into financial results and enterprise value (EV).
B8: How to play
B9: 1. Open each 'Round' tab. For all seven decision areas, pick ONE option from the dropdown in the yellow 'Your Choice' cell.
B10: 2. Watch the 'Engine' and 'Results' tabs update live — revenue, EBITDA, cash, risk and enterprise value.
B11: 3. Play Round 1, then Round 2, then Round 3. Each round opens from the prior round's closing position.
B12: 4. Compare teams on the 'Teams Dashboard'. Highest enterprise value at the end of Round 3 wins.
B14: How you are scored
B15: Enterprise Value = EBITDA × EV multiple. The multiple rises with recurring (SaaS) revenue mix and growth, and falls with operating risk. So short-term cuts can flatter EBITDA but shrink the multiple. Score = EV indexed to the starting EV (Start = 100), with a penalty if you run cash negative.
B17: The seven decision areas
... B24: • Corporate Functions — Overhead and the digital backbone (finance, IT, shared services).

Sheet Reference
A1: Key | B1: Area | C1: Option | D1: Spend $M | E1: Core g% | F1: Explore g% | G1: Margin pp | H1: Opex $M | I1: Risk | J1: Mult | K1: Recur pp | L1: Description
A2: Managing the Core (Exploit)|Harvest & cut | B2: Managing the Core (Exploit) | C2: Harvest & cut | D2: 0 | E2: -3 | F2: 0 | G2: 1.5 | H2: -40 | I2: 5 | J2: -0.5 | K2: 0 | L2: Maximise short-term cash from devices; minimal reinvestment.
A3: Managing the Core (Exploit)|Maintain | B3: Managing the Core (Exploit) | C3: Maintain | D3: 20 | E3: 0 | F3: 0 | G3: 0 | H3: 0 | I3: 0 | J3: 0 | K3: 0 | L3: Keep the core running as-is; protect share without big bets.
A4: Managing the Core (Exploit)|Optimise & defend | B4: Managing the Core (Exploit) | C4: Optimise & defend | D4: 60 | E4: 2 | F4: 0 | G4: 2 | H4: -10 | I4: -3 | J4: 0.3 | K4: 0 | L4: Lean + automation in plants; targeted upgrades to defend share.
A5: Managing the Core (Exploit)|Invest to grow core | B5: Managing the Core (Exploit) | C5: Invest to grow core | D5: 120 | E5: 5 | F5: 0 | G5: -0.5 | H5: 20 | I5: 3 | J5: 0.4 | K5: 0 | L5: New indications & geographies for the device line.
A6: Explore Portfolio|Pause exploration | B6: Explore Portfolio | C6: Pause exploration | D6: 0 | E6: 0 | F6: -10 | G6: 0.5 | H6: 0 | I6: 4 | J6: -1 | K6: 0 | L6: Freeze venture spend; bank the savings, accept slower SaaS.
A7: Explore Portfolio|Selective bets | B7: Explore Portfolio | C7: Selective bets | D7: 50 | E7: 0 | F7: 10 | G7: 0 | H7: 10 | I7: 0 | J7: 0.5 | K7: 2 | L7: Fund the 1-2 strongest digital-health products only.
A8: Explore Portfolio|Balanced portfolio | B8: Explore Portfolio | C8: Balanced portfolio | D8: 110 | E8: 0 | F8: 25 | G8: -0.5 | H8: 20 | I8: 2 | J8: 1.2 | K8: 3 | L8: A managed portfolio of SaaS bets across the pipeline.
A9: Explore Portfolio|Aggressive venture build | B9: Explore Portfolio | C9: Aggressive venture build | D9: 200 | E9: 0 | F9: 45 | G9: -1.5 | H9: 40 | I9: 6 | J9: 2 | K9: 5 | L9: Go big on the platform; chase category leadership in SaaS.
A10: Managing Disruption|Wait & see | B10: Managing Disruption | C10: Wait & see | D10: 0 | E10: -2 | F10: 0 | G10: 0 | H10: 0 | I10: 12 | J10: -1 | K10: 0 | L10: Hold position; assume the threat is over-hyped.
A11: Managing Disruption|Partner / license | B11: Managing Disruption | C11: Partner / license | D11: 40 | E11: 1 | F11: 0 | G11: 0 | H11: 0 | I11: -4 | J11: 0.5 | K11: 2 | L11: License AI / connectivity from a fast mover; integrate quickly.
A12: Managing Disruption|Acquire capability | B12: Managing Disruption | C12: Acquire capability | D12: 180 | E12: 3 | F12: 10 | G12: 0 | H12: 15 | I12: -6 | J12: 1 | K12: 3 | L12: Buy a disruptor to own the new platform outright.
A13: Managing Disruption|Build internal moonshot | B13: Managing Disruption | C13: Build internal moonshot | D13: 130 | E13: 0 | F13: 15 | G13: -1 | H13: 0 | I13: -2 | J13: 0.8 | K13: 2 | L13: Stand up a skunkworks to leapfrog the entrants.
... A29: Corporate Functions|Full digital core + shared services | B29: Corporate Functions | C29: Full digital core + shared services | D29: 140 | E29: 1 | F29: 0 | G29: 1 | H29: -45 | I29: -4 | J29: 0.6 | K29: 0 | L29: One digital backbone; shared services at scale.

Sheet Round 1
A1: ROUND 1 — Pressure on the Core
A2: Scenario: Reimbursement cuts squeeze device margins and an AI-diagnostics start-up lands its first hospital contracts. The board wants a plan that protects the core while standing up the digital-health platform.
A3: Decision Area | B3: Your Choice | C3: key | D3: Spend $M | E3: Core g% | F3: Explore g% | G3: Margin pp | H3: Opex $M | I3: Risk | J3: Mult | K3: Recur pp
A4: Managing the Core (Exploit) | B4: Maintain | C4: =A4&"|"&B4 | D4: =IFERROR(VLOOKUP($C4,Reference!$A:$K,4,FALSE),0) | E4: =IFERROR(VLOOKUP($C4,Reference!$A:$K,5,FALSE),0) | F4: =IFERROR(VLOOKUP($C4,Reference!$A:$K,6,FALSE),0) | G4: =IFERROR(VLOOKUP($C4,Reference!$A:$K,7,FALSE),0) | H4: =IFERROR(VLOOKUP($C4,Reference!$A:$K,8,FALSE),0) | I4: =IFERROR(VLOOKUP($C4,Reference!$A:$K,9,FALSE),0) | J4: =IFERROR(VLOOKUP($C4,Reference!$A:$K,10,FALSE),0) | K4: =IFERROR(VLOOKUP($C4,Reference!$A:$K,11,FALSE),0)
A5: Explore Portfolio | B5: Selective bets | C5: =A5&"|"&B5 | D5: =IFERROR(VLOOKUP($C5,Reference!$A:$K,4,FALSE),0) | E5: =IFERROR(VLOOKUP($C5,Reference!$A:$K,5,FALSE),0) | F5: =IFERROR(VLOOKUP($C5,Reference!$A:$K,6,FALSE),0) | G5: =IFERROR(VLOOKUP($C5,Reference!$A:$K,7,FALSE),0) | H5: =IFERROR(VLOOKUP($C5,Reference!$A:$K,8,FALSE),0) | I5: =IFERROR(VLOOKUP($C5,Reference!$A:$K,9,FALSE),0) | J5: =IFERROR(VLOOKUP($C5,Reference!$A:$K,10,FALSE),0) | K5: =IFERROR(VLOOKUP($C5,Reference!$A:$K,11,FALSE),0)
A6: Managing Disruption | B6: Partner / license | C6: =A6&"|"&B6 | D6: =IFERROR(VLOOKUP($C6,Reference!$A:$K,4,FALSE),0) | E6: =IFERROR(VLOOKUP($C6,Reference!$A:$K,5,FALSE),0) | F6: =IFERROR(VLOOKUP($C6,Reference!$A:$K,6,FALSE),0) | G6: =IFERROR(VLOOKUP($C6,Reference!$A:$K,7,FALSE),0) | H6: =IFERROR(VLOOKUP($C6,Reference!$A:$K,8,FALSE),0) | I6: =IFERROR(VLOOKUP($C6,Reference!$A:$K,9,FALSE),0) | J6: =IFERROR(VLOOKUP($C6,Reference!$A:$K,10,FALSE),0) | K6: =IFERROR(VLOOKUP($C6,Reference!$A:$K,11,FALSE),0)
A7: Supply Chain | B7: Dual-source | C7: =A7&"|"&B7 | D7: =IFERROR(VLOOKUP($C7,Reference!$A:$K,4,FALSE),0) | E7: =IFERROR(VLOOKUP($C7,Reference!$A:$K,5,FALSE),0) | F7: =IFERROR(VLOOKUP($C7,Reference!$A:$K,6,FALSE),0) | G7: =IFERROR(VLOOKUP($C7,Reference!$A:$K,7,FALSE),0) | H7: =IFERROR(VLOOKUP($C7,Reference!$A:$K,8,FALSE),0) | I7: =IFERROR(VLOOKUP($C7,Reference!$A:$K,9,FALSE),0) | J7: =IFERROR(VLOOKUP($C7,Reference!$A:$K,10,FALSE),0) | K7: =IFERROR(VLOOKUP($C7,Reference!$A:$K,11,FALSE),0)
A8: Revenue & Commercial Model | B8: Hold premium pricing | C8: =A8&"|"&B8 | D8: =IFERROR(VLOOKUP($C8,Reference!$A:$K,4,FALSE),0) | E8: =IFERROR(VLOOKUP($C8,Reference!$A:$K,5,FALSE),0) | F8: =IFERROR(VLOOKUP($C8,Reference!$A:$K,6,FALSE),0) | G8: =IFERROR(VLOOKUP($C8,Reference!$A:$K,7,FALSE),0) | H8: =IFERROR(VLOOKUP($C8,Reference!$A:$K,8,FALSE),0) | I8: =IFERROR(VLOOKUP($C8,Reference!$A:$K,9,FALSE),0) | J8: =IFERROR(VLOOKUP($C8,Reference!$A:$K,10,FALSE),0) | K8: =IFERROR(VLOOKUP($C8,Reference!$A:$K,11,FALSE),0)
A9: People & Talent | B9: Maintain | C9: =A9&"|"&B9 | D9: =IFERROR(VLOOKUP($C9,Reference!$A:$K,4,FALSE),0) | E9: =IFERROR(VLOOKUP($C9,Reference!$A:$K,5,FALSE),0) | F9: =IFERROR(VLOOKUP($C9,Reference!$A:$K,6,FALSE),0) | G9: =IFERROR(VLOOKUP($C9,Reference!$A:$K,7,FALSE),0) | H9: =IFERROR(VLOOKUP($C9,Reference!$A:$K,8,FALSE),0) | I9: =IFERROR(VLOOKUP($C9,Reference!$A:$K,9,FALSE),0) | J9: =IFERROR(VLOOKUP($C9,Reference!$A:$K,10,FALSE),0) | K9: =IFERROR(VLOOKUP($C9,Reference!$A:$K,11,FALSE),0)
A10: Corporate Functions | B10: Maintain | C10: =A10&"|"&B10 | D10: =IFERROR(VLOOKUP($C10,Reference!$A:$K,4,FALSE),0) | E10: =IFERROR(VLOOKUP($C10,Reference!$A:$K,5,FALSE),0) | F10: =IFERROR(VLOOKUP($C10,Reference!$A:$K,6,FALSE),0) | G10: =IFERROR(VLOOKUP($C10,Reference!$A:$K,7,FALSE),0) | H10: =IFERROR(VLOOKUP($C10,Reference!$A:$K,8,FALSE),0) | I10: =IFERROR(VLOOKUP($C10,Reference!$A:$K,9,FALSE),0) | J10: =IFERROR(VLOOKUP($C10,Reference!$A:$K,10,FALSE),0) | K10: =IFERROR(VLOOKUP($C10,Reference!$A:$K,11,FALSE),0)
A12: ROUND TOTALS | D12: =SUM(D4:D10) | E12: =SUM(E4:E10) | F12: =SUM(F4:F10) | G12: =SUM(G4:G10) | H12: =SUM(H4:H10) | I12: =SUM(I4:I10) | J12: =SUM(J4:J10) | K12: =SUM(K4:K10)

Sheet Round 2
A1: ROUND 2 — Disruption Accelerates
A2: Scenario: A rival launches a connected-device + subscription bundle, and a component shock exposes single-source supply. Investors start rewarding recurring revenue and punishing fragility.
A3: Decision Area | B3: Your Choice | C3: key | D3: Spend $M | E3: Core g% | F3: Explore g% | G3: Margin pp | H3: Opex $M | I3: Risk | J3: Mult | K3: Recur pp
A4: Managing the Core (Exploit) | B4: Maintain | C4: =A4&"|"&B4 | D4: =IFERROR(VLOOKUP($C4,Reference!$A:$K,4,FALSE),0) | E4: =IFERROR(VLOOKUP($C4,Reference!$A:$K,5,FALSE),0) | F4: =IFERROR(VLOOKUP($C4,Reference!$A:$K,6,FALSE),0) | G4: =IFERROR(VLOOKUP($C4,Reference!$A:$K,7,FALSE),0) | H4: =IFERROR(VLOOKUP($C4,Reference!$A:$K,8,FALSE),0) | I4: =IFERROR(VLOOKUP($C4,Reference!$A:$K,9,FALSE),0) | J4: =IFERROR(VLOOKUP($C4,Reference!$A:$K,10,FALSE),0) | K4: =IFERROR(VLOOKUP($C4,Reference!$A:$K,11,FALSE),0)
A5: Explore Portfolio | B5: Selective bets | C5: =A5&"|"&B5 | D5: =IFERROR(VLOOKUP($C5,Reference!$A:$K,4,FALSE),0) | E5: =IFERROR(VLOOKUP($C5,Reference!$A:$K,5,FALSE),0) | F5: =IFERROR(VLOOKUP($C5,Reference!$A:$K,6,FALSE),0) | G5: =IFERROR(VLOOKUP($C5,Reference!$A:$K,7,FALSE),0) | H5: =IFERROR(VLOOKUP($C5,Reference!$A:$K,8,FALSE),0) | I5: =IFERROR(VLOOKUP($C5,Reference!$A:$K,9,FALSE),0) | J5: =IFERROR(VLOOKUP($C5,Reference!$A:$K,10,FALSE),0) | K5: =IFERROR(VLOOKUP($C5,Reference!$A:$K,11,FALSE),0)
A6: Managing Disruption | B6: Partner / license | C6: =A6&"|"&B6 | D6: =IFERROR(VLOOKUP($C6,Reference!$A:$K,4,FALSE),0) | E6: =IFERROR(VLOOKUP($C6,Reference!$A:$K,5,FALSE),0) | F6: =IFERROR(VLOOKUP($C6,Reference!$A:$K,6,FALSE),0) | G6: =IFERROR(VLOOKUP($C6,Reference!$A:$K,7,FALSE),0) | H6: =IFERROR(VLOOKUP($C6,Reference!$A:$K,8,FALSE),0) | I6: =IFERROR(VLOOKUP($C6,Reference!$A:$K,9,FALSE),0) | J6: =IFERROR(VLOOKUP($C6,Reference!$A:$K,10,FALSE),0) | K6: =IFERROR(VLOOKUP($C6,Reference!$A:$K,11,FALSE),0)
A7: Supply Chain | B7: Dual-source | C7: =A7&"|"&B7 | D7: =IFERROR(VLOOKUP($C7,Reference!$A:$K,4,FALSE),0) | E7: =IFERROR(VLOOKUP($C7,Reference!$A:$K,5,FALSE),0) | F7: =IFERROR(VLOOKUP($C7,Reference!$A:$K,6,FALSE),0) | G7: =IFERROR(VLOOKUP($C7,Reference!$A:$K,7,FALSE),0) | H7: =IFERROR(VLOOKUP($C7,Reference!$A:$K,8,FALSE),0) | I7: =IFERROR(VLOOKUP($C7,Reference!$A:$K,9,FALSE),0) | J7: =IFERROR(VLOOKUP($C7,Reference!$A:$K,10,FALSE),0) | K7: =IFERROR(VLOOKUP($C7,Reference!$A:$K,11,FALSE),0)
A8: Revenue & Commercial Model | B8: Hold premium pricing | C8: =A8&"|"&B8 | D8: =IFERROR(VLOOKUP($C8,Reference!$A:$K,4,FALSE),0) | E8: =IFERROR(VLOOKUP($C8,Reference!$A:$K,5,FALSE),0) | F8: =IFERROR(VLOOKUP($C8,Reference!$A:$K,6,FALSE),0) | G8: =IFERROR(VLOOKUP($C8,Reference!$A:$K,7,FALSE),0) | H8: =IFERROR(VLOOKUP($C8,Reference!$A:$K,8,FALSE),0) | I8: =IFERROR(VLOOKUP($C8,Reference!$A:$K,9,FALSE),0) | J8: =IFERROR(VLOOKUP($C8,Reference!$A:$K,10,FALSE),0) | K8: =IFERROR(VLOOKUP($C8,Reference!$A:$K,11,FALSE),0)
A9: People & Talent | B9: Maintain | C9: =A9&"|"&B9 | D9: =IFERROR(VLOOKUP($C9,Reference!$A:$K,4,FALSE),0) | E9: =IFERROR(VLOOKUP($C9,Reference!$A:$K,5,FALSE),0) | F9: =IFERROR(VLOOKUP($C9,Reference!$A:$K,6,FALSE),0) | G9: =IFERROR(VLOOKUP($C9,Reference!$A:$K,7,FALSE),0) | H9: =IFERROR(VLOOKUP($C9,Reference!$A:$K,8,FALSE),0) | I9: =IFERROR(VLOOKUP($C9,Reference!$A:$K,9,FALSE),0) | J9: =IFERROR(VLOOKUP($C9,Reference!$A:$K,10,FALSE),0) | K9: =IFERROR(VLOOKUP($C9,Reference!$A:$K,11,FALSE),0)
A10: Corporate Functions | B10: Maintain | C10: =A10&"|"&B10 | D10: =IFERROR(VLOOKUP($C10,Reference!$A:$K,4,FALSE),0) | E10: =IFERROR(VLOOKUP($C10,Reference!$A:$K,5,FALSE),0) | F10: =IFERROR(VLOOKUP($C10,Reference!$A:$K,6,FALSE),0) | G10: =IFERROR(VLOOKUP($C10,Reference!$A:$K,7,FALSE),0) | H10: =IFERROR(VLOOKUP($C10,Reference!$A:$K,8,FALSE),0) | I10: =IFERROR(VLOOKUP($C10,Reference!$A:$K,9,FALSE),0) | J10: =IFERROR(VLOOKUP($C10,Reference!$A:$K,10,FALSE),0) | K10: =IFERROR(VLOOKUP($C10,Reference!$A:$K,11,FALSE),0)
A12: ROUND TOTALS | D12: =SUM(D4:D10) | E12: =SUM(E4:E10) | F12: =SUM(F4:F10) | G12: =SUM(G4:G10) | H12: =SUM(H4:H10) | I12: =SUM(I4:I10) | J12: =SUM(J4:J10) | K12: =SUM(K4:K10)

Sheet Round 3
A1: ROUND 3 — The New Normal
A2: Scenario: Value-based care mandates reshape buying. The market now prizes recurring SaaS revenue, proven innovation and low operating risk. Time to convert your build-up into enterprise value.
A3: Decision Area | B3: Your Choice | C3: key | D3: Spend $M | E3: Core g% | F3: Explore g% | G3: Margin pp | H3: Opex $M | I3: Risk | J3: Mult | K3: Recur pp
A4: Managing the Core (Exploit) | B4: Maintain | C4: =A4&"|"&B4 | D4: =IFERROR(VLOOKUP($C4,Reference!$A:$K,4,FALSE),0) | E4: =IFERROR(VLOOKUP($C4,Reference!$A:$K,5,FALSE),0) | F4: =IFERROR(VLOOKUP($C4,Reference!$A:$K,6,FALSE),0) | G4: =IFERROR(VLOOKUP($C4,Reference!$A:$K,7,FALSE),0) | H4: =IFERROR(VLOOKUP($C4,Reference!$A:$K,8,FALSE),0) | I4: =IFERROR(VLOOKUP($C4,Reference!$A:$K,9,FALSE),0) | J4: =IFERROR(VLOOKUP($C4,Reference!$A:$K,10,FALSE),0) | K4: =IFERROR(VLOOKUP($C4,Reference!$A:$K,11,FALSE),0)
A5: Explore Portfolio | B5: Selective bets | C5: =A5&"|"&B5 | D5: =IFERROR(VLOOKUP($C5,Reference!$A:$K,4,FALSE),0) | E5: =IFERROR(VLOOKUP($C5,Reference!$A:$K,5,FALSE),0) | F5: =IFERROR(VLOOKUP($C5,Reference!$A:$K,6,FALSE),0) | G5: =IFERROR(VLOOKUP($C5,Reference!$A:$K,7,FALSE),0) | H5: =IFERROR(VLOOKUP($C5,Reference!$A:$K,8,FALSE),0) | I5: =IFERROR(VLOOKUP($C5,Reference!$A:$K,9,FALSE),0) | J5: =IFERROR(VLOOKUP($C5,Reference!$A:$K,10,FALSE),0) | K5: =IFERROR(VLOOKUP($C5,Reference!$A:$K,11,FALSE),0)
A6: Managing Disruption | B6: Partner / license | C6: =A6&"|"&B6 | D6: =IFERROR(VLOOKUP($C6,Reference!$A:$K,4,FALSE),0) | E6: =IFERROR(VLOOKUP($C6,Reference!$A:$K,5,FALSE),0) | F6: =IFERROR(VLOOKUP($C6,Reference!$A:$K,6,FALSE),0) | G6: =IFERROR(VLOOKUP($C6,Reference!$A:$K,7,FALSE),0) | H6: =IFERROR(VLOOKUP($C6,Reference!$A:$K,8,FALSE),0) | I6: =IFERROR(VLOOKUP($C6,Reference!$A:$K,9,FALSE),0) | J6: =IFERROR(VLOOKUP($C6,Reference!$A:$K,10,FALSE),0) | K6: =IFERROR(VLOOKUP($C6,Reference!$A:$K,11,FALSE),0)
A7: Supply Chain | B7: Dual-source | C7: =A7&"|"&B7 | D7: =IFERROR(VLOOKUP($C7,Reference!$A:$K,4,FALSE),0) | E7: =IFERROR(VLOOKUP($C7,Reference!$A:$K,5,FALSE),0) | F7: =IFERROR(VLOOKUP($C7,Reference!$A:$K,6,FALSE),0) | G7: =IFERROR(VLOOKUP($C7,Reference!$A:$K,7,FALSE),0) | H7: =IFERROR(VLOOKUP($C7,Reference!$A:$K,8,FALSE),0) | I7: =IFERROR(VLOOKUP($C7,Reference!$A:$K,9,FALSE),0) | J7: =IFERROR(VLOOKUP($C7,Reference!$A:$K,10,FALSE),0) | K7: =IFERROR(VLOOKUP($C7,Reference!$A:$K,11,FALSE),0)
A8: Revenue & Commercial Model | B8: Hold premium pricing | C8: =A8&"|"&B8 | D8: =IFERROR(VLOOKUP($C8,Reference!$A:$K,4,FALSE),0) | E8: =IFERROR(VLOOKUP($C8,Reference!$A:$K,5,FALSE),0) | F8: =IFERROR(VLOOKUP($C8,Reference!$A:$K,6,FALSE),0) | G8: =IFERROR(VLOOKUP($C8,Reference!$A:$K,7,FALSE),0) | H8: =IFERROR(VLOOKUP($C8,Reference!$A:$K,8,FALSE),0) | I8: =IFERROR(VLOOKUP($C8,Reference!$A:$K,9,FALSE),0) | J8: =IFERROR(VLOOKUP($C8,Reference!$A:$K,10,FALSE),0) | K8: =IFERROR(VLOOKUP($C8,Reference!$A:$K,11,FALSE),0)
A9: People & Talent | B9: Maintain | C9: =A9&"|"&B9 | D9: =IFERROR(VLOOKUP($C9,Reference!$A:$K,4,FALSE),0) | E9: =IFERROR(VLOOKUP($C9,Reference!$A:$K,5,FALSE),0) | F9: =IFERROR(VLOOKUP($C9,Reference!$A:$K,6,FALSE),0) | G9: =IFERROR(VLOOKUP($C9,Reference!$A:$K,7,FALSE),0) | H9: =IFERROR(VLOOKUP($C9,Reference!$A:$K,8,FALSE),0) | I9: =IFERROR(VLOOKUP($C9,Reference!$A:$K,9,FALSE),0) | J9: =IFERROR(VLOOKUP($C9,Reference!$A:$K,10,FALSE),0) | K9: =IFERROR(VLOOKUP($C9,Reference!$A:$K,11,FALSE),0)
A10: Corporate Functions | B10: Maintain | C10: =A10&"|"&B10 | D10: =IFERROR(VLOOKUP($C10,Reference!$A:$K,4,FALSE),0) | E10: =IFERROR(VLOOKUP($C10,Reference!$A:$K,5,FALSE),0) | F10: =IFERROR(VLOOKUP($C10,Reference!$A:$K,6,FALSE),0) | G10: =IFERROR(VLOOKUP($C10,Reference!$A:$K,7,FALSE),0) | H10: =IFERROR(VLOOKUP($C10,Reference!$A:$K,8,FALSE),0) | I10: =IFERROR(VLOOKUP($C10,Reference!$A:$K,9,FALSE),0) | J10: =IFERROR(VLOOKUP($C10,Reference!$A:$K,10,FALSE),0) | K10: =IFERROR(VLOOKUP($C10,Reference!$A:$K,11,FALSE),0)
A12: ROUND TOTALS | D12: =SUM(D4:D10) | E12: =SUM(E4:E10) | F12: =SUM(F4:F10) | G12: =SUM(G4:G10) | H12: =SUM(H4:H10) | I12: =SUM(I4:I10) | J12: =SUM(J4:J10) | K12: =SUM(K4:K10)

Sheet Engine
A1: FINANCIAL ENGINE ($M unless noted)
A2: Metric | B2: Start | C2: Round 1 | D2: Round 2 | E2: Round 3
A3: Core revenue (devices) | B3: 1800 | C3: =B3*(1+(1.5+'Round 1'!E12)/100) | D3: =C3*(1+(1.5+'Round 2'!E12)/100) | E3: =D3*(1+(1.5+'Round 3'!E12)/100)
A4: Explore revenue (SaaS/ventures) | B4: 200 | C4: =B4*(1+(8.0+'Round 1'!F12)/100) | D4: =C4*(1+(8.0+'Round 2'!F12)/100) | E4: =D4*(1+(8.0+'Round 3'!F12)/100)
A5: Total revenue | B5: =B3+B4 | C5: =C3+C4 | D5: =D3+D4 | E5: =E3+E4
A6: Revenue growth % | B6: 0 | C6: =C5/B5-1 | D6: =D5/C5-1 | E6: =E5/D5-1
A7: Gross margin % | B7: 60 | C7: =B7+'Round 1'!G12 | D7: =C7+'Round 2'!G12 | E7: =D7+'Round 3'!G12
A8: Gross profit | B8: =B5*B7/100 | C8: =C5*C7/100 | D8: =D5*D7/100 | E8: =E5*E7/100
A9: Operating costs (recurring) | B9: 700 | C9: =B9+'Round 1'!H12 | D9: =C9+'Round 2'!H12 | E9: =D9+'Round 3'!H12
A10: EBITDA | B10: =B8-B9 | C10: =C8-C9 | D10: =D8-D9 | E10: =E8-E9
A11: EBITDA margin % | B11: =B10/B5 | C11: =C10/C5 | D11: =D10/D5 | E11: =E10/E5
A12: Investment spend (one-time) | B12: 0 | C12: ='Round 1'!D12 | D12: ='Round 2'!D12 | E12: ='Round 3'!D12
A13: Cash balance | B13: 300 | C13: =B13+C10-C12 | D13: =C13+D10-D12 | E13: =D13+E10-E12
A14: Risk index (0-100, lower better) | B14: 30 | C14: =MEDIAN(0,B14+'Round 1'!I12,100) | D14: =MEDIAN(0,C14+'Round 2'!I12,100) | E14: =MEDIAN(0,D14+'Round 3'!I12,100)
A15: Recurring revenue mix % | B15: 15 | C15: =MEDIAN(0,B15+'Round 1'!K12,90) | D15: =MEDIAN(0,C15+'Round 2'!K12,90) | E15: =MEDIAN(0,D15+'Round 3'!K12,90)
A16: Cumulative multiple adj. | B16: 0 | C16: =B16+'Round 1'!J12 | D16: =C16+'Round 2'!J12 | E16: =D16+'Round 3'!J12
A17: EV multiple (x) | B17: =MAX(6.0,MIN(18.0,9.0+B16+B15/100*6.0+B6*100*0.15-(B14-30.0)*0.05)) | C17: =MAX(6.0,MIN(18.0,9.0+C16+C15/100*6.0+C6*100*0.15-(C14-30.0)*0.05)) | D17: =MAX(6.0,MIN(18.0,9.0+D16+D15/100*6.0+D6*100*0.15-(D14-30.0)*0.05)) | E17: =MAX(6.0,MIN(18.0,9.0+E16+E15/100*6.0+E6*100*0.15-(E14-30.0)*0.05))
A18: ENTERPRISE VALUE | B18: =B10*B17 | C18: =C10*C17 | D18: =D10*D17 | E18: =E10*E17
A19: EV change vs Start | B19: 0 | C19: =C18-B18 | D19: =D18-B18 | E19: =E18-B18
A20: SCORE (Start = 100) | B20: 100 | C20: =C18/$B$18*100-MAX(0,-C13)*0.1 | D20: =D18/$B$18*100-MAX(0,-D13)*0.1 | E20: =E18/$B$18*100-MAX(0,-E13)*0.1

Sheet Results
A1: RESULTS

Sheet Teams Dashboard
A1: TEAMS DASHBOARD — LEADERBOARD (end of Round 3)
A2: Row 1 reflects THIS workbook automatically. Facilitator: type each other team's final figures into rows below to rank the room.
A3: Rank | B3: Team | C3: Enterprise Value $M | D3: EV vs Start $M | E3: Recurring mix % | F3: Risk | G3: Score
A4: =IF(C4="","",RANK(C4,$C$4:$C$11)) | B4: Your Team | C4: =Engine!E18 | D4: =Engine!E19 | E4: =Engine!E15 | F4: =Engine!E14 | G4: =Engine!E20
A5: =IF(C5="","",RANK(C5,$C$4:$C$11)) | B5: Team 2
A6: =IF(C6="","",RANK(C6,$C$4:$C$11)) | B6: Team 3
A7: =IF(C7="","",RANK(C7,$C$4:$C$11)) | B7: Team 4
A8: =IF(C8="","",RANK(C8,$C$4:$C$11)) | B8: Team 5
A9: =IF(C9="","",RANK(C9,$C$4:$C$11)) | B9: Team 6
A10: =IF(C10="","",RANK(C10,$C$4:$C$11)) | B10: Team 7
A11: =IF(C11="","",RANK(C11,$C$4:$C$11)) | B11: Team 8
